edc_egfr/__init__.py
edc_egfr/apps.py
edc_egfr/constants.py
edc_egfr/egfr.py
edc_egfr/get_drop_notification_model.py
edc_egfr/get_egfr_for_subject.py
edc_egfr/admin/__init__.py
edc_egfr/admin/egfr_drop_notification_admin_mixin.py
edc_egfr/calculators/__init__.py
edc_egfr/calculators/base_egrfr.py
edc_egfr/calculators/egfr_ckd_epi.py
edc_egfr/calculators/egfr_cockcroft_gault.py
edc_egfr/calculators/percent_change.py
edc_egfr/form_validator_mixins/__init__.py
edc_egfr/form_validator_mixins/egfr_form_validator_mixins.py
edc_egfr/model_mixins/__init__.py
edc_egfr/model_mixins/egfr_drop_notification_model_mixin.py
edc_egfr/model_mixins/egfr_model_mixin.py
edc_egfr/tests/__init__.py
edc_egfr/tests/models.py
edc_egfr/tests/test_settings.py
edc_egfr/tests/urls.py
edc_egfr/tests/etc/user-aes-local.key
edc_egfr/tests/etc/user-aes-restricted.key
edc_egfr/tests/etc/user-rsa-local-private.pem
edc_egfr/tests/etc/user-rsa-local-public.pem
edc_egfr/tests/etc/user-rsa-restricted-private.pem
edc_egfr/tests/etc/user-rsa-restricted-public.pem
edc_egfr/tests/etc/user-salt-local.key
edc_egfr/tests/etc/user-salt-restricted.key
edc_egfr/tests/tests/__init__.py
edc_egfr/tests/tests/test_calculators.py
edc_egfr/tests/tests/test_drop_notification.py
edc_egfr/tests/tests/test_egfr.py
edc_egfr-1.0.2.dist-info/licenses/AUTHORS
edc_egfr-1.0.2.dist-info/licenses/LICENSE
egfr_app/__init__.py
egfr_app/admin.py
egfr_app/apps.py
egfr_app/consents.py
egfr_app/form_validators.py
egfr_app/lab_profiles.py
egfr_app/models.py
egfr_app/reportables.py
egfr_app/urls.py
egfr_app/visit_schedules.py
egfr_app/migrations/__init__.py
edc_egfr-1.0.2.dist-info/METADATA
edc_egfr-1.0.2.dist-info/WHEEL
edc_egfr-1.0.2.dist-info/top_level.txt
edc_egfr-1.0.2.dist-info/RECORD
